pylab_crawler_sdk/__init__.py
pylab_crawler_sdk-1.4.3.dist-info/LICENSE
pylab_crawler_sdk-1.4.3.dist-info/METADATA
pylab_crawler_sdk-1.4.3.dist-info/WHEEL
pylab_crawler_sdk-1.4.3.dist-info/top_level.txt
pylab_crawler_sdk-1.4.3.dist-info/RECORD
