Metadata-Version: 2.1
Name: pylab-crawler-sdk
Version: 1.4.3
Summary: SDK for https://crawler.pylab.co
Home-page: https://github.com/PyLabCo/pylab-crawler-sdk
Author: PyLab
Author-email: yeongbin.jo@pylab.co
License: MIT
Keywords: sdk
Platform: UNKNOWN
Classifier: Development Status :: 5 - Production/Stable
Classifier: Topic :: Software Development :: Testing
Classifier: Topic :: System :: Installation/Setup
Classifier: Topic :: Software Development :: Libraries :: Python Modules
Classifier: License :: OSI Approved :: MIT License
Classifier: Programming Language :: Python :: 3
Classifier: Programming Language :: Python :: 3.8
Requires-Python: >=3
Requires-Dist: requests
